{"frames": [

{
	"filename": "body.png",
	"frame": {"x":324,"y":2,"w":97,"h":95},
	"rotated": true,
	"trimmed": false,
	"spriteSourceSize": {"x":0,"y":0,"w":97,"h":95},
	"sourceSize": {"w":97,"h":95},
	"pivot": {"x":0.5,"y":0.5}
},
{
	"filename": "cape.png",
	"frame": {"x":176,"y":2,"w":146,"h":159},
	"rotated": false,
	"trimmed": false,
	"spriteSourceSize": {"x":0,"y":0,"w":146,"h":159},
	"sourceSize": {"w":146,"h":159},
	"pivot": {"x":0.5,"y":0.5}
},
{
	"filename": "eyes.png",
	"frame": {"x":220,"y":220,"w":82,"h":31},
	"rotated": false,
	"trimmed": false,
	"spriteSourceSize": {"x":0,"y":0,"w":82,"h":31},
	"sourceSize": {"w":82,"h":31},
	"pivot": {"x":0.5,"y":0.5}
},
{
	"filename": "fingers.png",
	"frame": {"x":343,"y":220,"w":31,"h":33},
	"rotated": false,
	"trimmed": false,
	"spriteSourceSize": {"x":0,"y":0,"w":31,"h":33},
	"sourceSize": {"w":31,"h":33},
	"pivot": {"x":0.5,"y":0.5}
},
{
	"filename": "foot1.png",
	"frame": {"x":455,"y":96,"w":50,"h":42},
	"rotated": false,
	"trimmed": false,
	"spriteSourceSize": {"x":0,"y":0,"w":50,"h":42},
	"sourceSize": {"w":50,"h":42},
	"pivot": {"x":0.5,"y":0.5}
},
{
	"filename": "foot2.png",
	"frame": {"x":469,"y":140,"w":53,"h":38},
	"rotated": true,
	"trimmed": false,
	"spriteSourceSize": {"x":0,"y":0,"w":53,"h":38},
	"sourceSize": {"w":53,"h":38},
	"pivot": {"x":0.5,"y":0.5}
},
{
	"filename": "forearm1.png",
	"frame": {"x":472,"y":195,"w":41,"h":49},
	"rotated": false,
	"trimmed": false,
	"spriteSourceSize": {"x":0,"y":0,"w":41,"h":49},
	"sourceSize": {"w":41,"h":49},
	"pivot": {"x":0.5,"y":0.5}
},
{
	"filename": "forearm2.png",
	"frame": {"x":376,"y":218,"w":31,"h":32},
	"rotated": false,
	"trimmed": false,
	"spriteSourceSize": {"x":0,"y":0,"w":31,"h":32},
	"sourceSize": {"w":31,"h":32},
	"pivot": {"x":0.5,"y":0.5}
},
{
	"filename": "hand1.png",
	"frame": {"x":477,"y":2,"w":37,"h":48},
	"rotated": false,
	"trimmed": false,
	"spriteSourceSize": {"x":0,"y":0,"w":37,"h":48},
	"sourceSize": {"w":37,"h":48},
	"pivot": {"x":0.5,"y":0.5}
},
{
	"filename": "hand2.png",
	"frame": {"x":304,"y":220,"w":31,"h":37},
	"rotated": true,
	"trimmed": false,
	"spriteSourceSize": {"x":0,"y":0,"w":31,"h":37},
	"sourceSize": {"w":31,"h":37},
	"pivot": {"x":0.5,"y":0.5}
},
{
	"filename": "head.png",
	"frame": {"x":2,"y":2,"w":172,"h":173},
	"rotated": false,
	"trimmed": false,
	"spriteSourceSize": {"x":0,"y":0,"w":172,"h":173},
	"sourceSize": {"w":172,"h":173},
	"pivot": {"x":0.5,"y":0.5}
},
{
	"filename": "mantles.png",
	"frame": {"x":220,"y":163,"w":136,"h":55},
	"rotated": false,
	"trimmed": false,
	"spriteSourceSize": {"x":0,"y":0,"w":136,"h":55},
	"sourceSize": {"w":136,"h":55},
	"pivot": {"x":0.5,"y":0.5}
},
{
	"filename": "mouth.png",
	"frame": {"x":409,"y":218,"w":61,"h":13},
	"rotated": false,
	"trimmed": false,
	"spriteSourceSize": {"x":0,"y":0,"w":61,"h":13},
	"sourceSize": {"w":61,"h":13},
	"pivot": {"x":0.5,"y":0.5}
},
{
	"filename": "shin1.png",
	"frame": {"x":358,"y":163,"w":53,"h":57},
	"rotated": true,
	"trimmed": false,
	"spriteSourceSize": {"x":0,"y":0,"w":53,"h":57},
	"sourceSize": {"w":53,"h":57},
	"pivot": {"x":0.5,"y":0.5}
},
{
	"filename": "shin2.png",
	"frame": {"x":421,"y":2,"w":51,"h":54},
	"rotated": true,
	"trimmed": false,
	"spriteSourceSize": {"x":0,"y":0,"w":51,"h":54},
	"sourceSize": {"w":51,"h":54},
	"pivot": {"x":0.5,"y":0.5}
},
{
	"filename": "sword.png",
	"frame": {"x":2,"y":177,"w":216,"h":69},
	"rotated": false,
	"trimmed": false,
	"spriteSourceSize": {"x":0,"y":0,"w":216,"h":69},
	"sourceSize": {"w":216,"h":69},
	"pivot": {"x":0.5,"y":0.5}
},
{
	"filename": "thigh1.png",
	"frame": {"x":324,"y":101,"w":60,"h":63},
	"rotated": true,
	"trimmed": false,
	"spriteSourceSize": {"x":0,"y":0,"w":60,"h":63},
	"sourceSize": {"w":60,"h":63},
	"pivot": {"x":0.5,"y":0.5}
},
{
	"filename": "thigh2.png",
	"frame": {"x":389,"y":101,"w":57,"h":64},
	"rotated": true,
	"trimmed": false,
	"spriteSourceSize": {"x":0,"y":0,"w":57,"h":64},
	"sourceSize": {"w":57,"h":64},
	"pivot": {"x":0.5,"y":0.5}
},
{
	"filename": "upperarm1.png",
	"frame": {"x":417,"y":160,"w":50,"h":56},
	"rotated": false,
	"trimmed": false,
	"spriteSourceSize": {"x":0,"y":0,"w":50,"h":56},
	"sourceSize": {"w":50,"h":56},
	"pivot": {"x":0.5,"y":0.5}
},
{
	"filename": "upperarm2.png",
	"frame": {"x":421,"y":55,"w":39,"h":59},
	"rotated": true,
	"trimmed": false,
	"spriteSourceSize": {"x":0,"y":0,"w":39,"h":59},
	"sourceSize": {"w":39,"h":59},
	"pivot": {"x":0.5,"y":0.5}
}],
"meta": {
	"app": "http://www.codeandweb.com/texturepacker",
	"version": "1.0",
	"image": "hero-mesh.png",
	"format": "RGBA8888",
	"size": {"w":516,"h":255},
	"scale": "1",
	"smartupdate": "$TexturePacker:SmartUpdate:31f5adf9f899c655ab53382bb302149a:8a39cbdc781e1ab2623aa22fbce37020:705b21505bf8c1d5ea944192141cd546$"
}
}
